hanlp/__init__.py
hanlp/version.py
hanlp/callbacks/__init__.py
hanlp/callbacks/fine_csv_logger.py
hanlp/common/__init__.py
hanlp/common/component.py
hanlp/common/dataset.py
hanlp/common/keras_component.py
hanlp/common/structure.py
hanlp/common/torch_component.py
hanlp/common/transform.py
hanlp/common/transform_tf.py
hanlp/common/vocab.py
hanlp/common/vocab_tf.py
hanlp/components/__init__.py
hanlp/components/lambda_wrapper.py
hanlp/components/lemmatizer.py
hanlp/components/pipeline.py
hanlp/components/rnn_language_model_tf.py
hanlp/components/amr/__init__.py
hanlp/components/amr/amrbart/__init__.py
hanlp/components/amr/amrbart/bart_amr_generation.py
hanlp/components/amr/amrbart/bart_amr_parser.py
hanlp/components/amr/amrbart/common/__init__.py
hanlp/components/amr/amrbart/common/constant.py
hanlp/components/amr/amrbart/common/penman_interface.py
hanlp/components/amr/amrbart/common/postprocessing.py
hanlp/components/amr/amrbart/data_interface/__init__.py
hanlp/components/amr/amrbart/data_interface/dataset.py
hanlp/components/amr/amrbart/model_interface/__init__.py
hanlp/components/amr/amrbart/model_interface/modeling_bart.py
hanlp/components/amr/amrbart/model_interface/tokenization_bart.py
hanlp/components/amr/amrbart/preprocess/__init__.py
hanlp/components/amr/amrbart/preprocess/amr_io.py
hanlp/components/amr/amrbart/preprocess/penman_interface.py
hanlp/components/amr/amrbart/preprocess/read_and_process.py
hanlp/components/amr/seq2seq/__init__.py
hanlp/components/amr/seq2seq/evaluation.py
hanlp/components/amr/seq2seq/optim.py
hanlp/components/amr/seq2seq/seq2seq_amr_parser.py
hanlp/components/amr/seq2seq/dataset/IO.py
hanlp/components/amr/seq2seq/dataset/__init__.py
hanlp/components/amr/seq2seq/dataset/dataset.py
hanlp/components/amr/seq2seq/dataset/linearization.py
hanlp/components/amr/seq2seq/dataset/penman.py
hanlp/components/amr/seq2seq/dataset/postprocessing.py
hanlp/components/amr/seq2seq/dataset/tokenization_bart.py
hanlp-2.1.3.dist-info/LICENSE
hanlp-2.1.3.dist-info/METADATA
hanlp-2.1.3.dist-info/WHEEL
hanlp-2.1.3.dist-info/top_level.txt
hanlp-2.1.3.dist-info/RECORD
