Metadata-Version: 2.1
Name: hanlp
Version: 2.1.3
Summary: HanLP: Han Language Processing
Home-page: https://github.com/hankcs/HanLP
Author: hankcs
Author-email: hankcshe@gmail.com
License: Apache License 2.0
Keywords: corpus,machine-learning,NLU,NLP
Classifier: Intended Audience :: Science/Research
Classifier: Intended Audience :: Developers
Classifier: Development Status :: 4 - Beta
Classifier: Operating System :: OS Independent
Classifier: License :: OSI Approved :: Apache Software License
Classifier: Programming Language :: Python :: 3.6
Classifier: Programming Language :: Python :: 3.7
Classifier: Programming Language :: Python :: 3.8
Classifier: Programming Language :: Python :: 3.9
Classifier: Programming Language :: Python :: 3.10
Classifier: Topic :: Scientific/Engineering :: Artificial Intelligence
Classifier: Topic :: Text Processing :: Linguistic
Requires-Python: >=3.6
Provides-Extra: amr
Provides-Extra: fasttext
Provides-Extra: full
Provides-Extra: tf
License-File: LICENSE
